aiocogeo/__init__.py
aiocogeo/cog.py
aiocogeo/compression.py
aiocogeo/config.py
aiocogeo/constants.py
aiocogeo/errors.py
aiocogeo/filesystems.py
aiocogeo/ifd.py
aiocogeo/partial_reads.py
aiocogeo/stac.py
aiocogeo/tag.py
aiocogeo/utils.py
aiocogeo/scripts/__init__.py
aiocogeo/scripts/cli.py
aiocogeo-0.3.0.dist-info/LICENSE
aiocogeo-0.3.0.dist-info/METADATA
aiocogeo-0.3.0.dist-info/WHEEL
aiocogeo-0.3.0.dist-info/entry_points.txt
aiocogeo-0.3.0.dist-info/top_level.txt
aiocogeo-0.3.0.dist-info/RECORD
