Metadata-Version: 2.1
Name: aiocogeo
Version: 0.3.0
Summary: Asynchronous cogeotiff reader
Home-page: https://github.com/geospatial-jeff/aiocogeo
Author: Jeff Albrecht
Author-email: geospatialjeff@gmail.com
License: mit
Keywords: cogeo COG
Platform: UNKNOWN
Classifier: Intended Audience :: Developers
Classifier: Intended Audience :: Information Technology
Classifier: Intended Audience :: Science/Research
Classifier: Programming Language :: Python :: 3.6
Classifier: Programming Language :: Python :: 3.7
Classifier: Programming Language :: Python :: 3.8
Classifier: License :: OSI Approved :: MIT License
Requires-Python: >=3.7
Requires-Dist: aiofiles
Requires-Dist: aiohttp (<=3.6.2)
Requires-Dist: aiocache
Requires-Dist: affine
Requires-Dist: imagecodecs
Requires-Dist: typer
Requires-Dist: Pillow
Requires-Dist: stac-pydantic (>=1.3.*)
Requires-Dist: geojson-pydantic (==0.1.0)
Requires-Dist: xmltodict
Provides-Extra: dev
Requires-Dist: mercantile ; extra == 'dev'
Requires-Dist: morecantile ; extra == 'dev'
Requires-Dist: rasterio ; extra == 'dev'
Requires-Dist: rio-tiler (==2.0b9) ; extra == 'dev'
Requires-Dist: pytest (<5.4) ; extra == 'dev'
Requires-Dist: pytest-asyncio (<0.11.0) ; extra == 'dev'
Requires-Dist: pytest-cov ; extra == 'dev'
Requires-Dist: shapely ; extra == 'dev'
Requires-Dist: botocore (==1.15.32) ; extra == 'dev'
Requires-Dist: boto3 (==1.12.32) ; extra == 'dev'
Requires-Dist: aioboto3 ; extra == 'dev'
Provides-Extra: s3
Requires-Dist: aioboto3 ; extra == 's3'
